<?xml version="1.0" encoding="UTF-8"?>
<!DOCTYPE mapper PUBLIC "-//mybatis.org//DTD Mapper 3.0//EN" "http://mybatis.org/dtd/mybatis-3-mapper.dtd">

<mapper namespace="com.ecommercesystemtemplate.warehouse.dao.WareSkuDao">

	<!-- 可根据自己的需求，是否要使用 -->
    <resultMap type="com.ecommercesystemtemplate.warehouse.entity.WareSkuEntity" id="wareSkuMap">
        <result property="id" column="id"/>
        <result property="skuId" column="sku_id"/>
        <result property="wareId" column="ware_id"/>
        <result property="stock" column="stock"/>
        <result property="skuName" column="sku_name"/>
        <result property="stockLocked" column="stock_locked"/>
    </resultMap>
    <update id="addStock">
        update wms_ware_sku set stock = stock + #{skuNum} where ware_id = #{wareId} and sku_id = #{skuId}
    </update>

    <update id="lockStock">
        update wms_ware_sku set  stock_locked = stock_locked + #{num} where sku_id = #{skuId}
        and ware_id = #{wareId} and stock - stock_locked >= #{num}
    </update>

    <update id="unlockStock">
        update wms_ware_sku set stock_locked = stock_locked - #{skuNum}
        where sku_id = #{skuId} and ware_id = #{wareId}
    </update>

    <select id="getSkuHasStock" resultType="java.lang.Long">
        select sum(stock - stock_locked) from wms_ware_sku where sku_id = #{skuId}
    </select>

    <select id="listWareIdHasSku" resultType="java.lang.Long">
        select ware_id from wms_ware_sku where sku_id=#{skuId} and stock-stock_locked > 0
    </select>


</mapper>
